talkscript2media/__init__.py
talkscript2media/__main__.py
talkscript2media/storage.py
talkscript2media/text_to_audio.py
talkscript2media/to_video.py
talkscript2media-0.1.0.dev0.dist-info/DESCRIPTION.rst
talkscript2media-0.1.0.dev0.dist-info/METADATA
talkscript2media-0.1.0.dev0.dist-info/RECORD
talkscript2media-0.1.0.dev0.dist-info/WHEEL
talkscript2media-0.1.0.dev0.dist-info/entry_points.txt
talkscript2media-0.1.0.dev0.dist-info/metadata.json
talkscript2media-0.1.0.dev0.dist-info/top_level.txt
