Metadata-Version: 2.0
Name: talkscript2media
Version: 0.1.0.dev0
Summary: Convert a talk script and a set of slides to video
Home-page: https://github.com/cosmoscalibur/talkscript2media
Author: Edward Villegas-Pulgarin <cosmoscalibur@gmail.com>, Manuela Jaramillo <manujarare@hotmail.com>
Author-email: cosmoscalibur@gmail.com
License: MIT
Keywords: talks video slides tutorial video-tutorial
Platform: UNKNOWN
Classifier: Development Status :: 2 - Pre-Alpha
Classifier: Environment :: Console
Classifier: Intended Audience :: End Users/Desktop
Classifier: Intended Audience :: Other Audience
Classifier: License :: OSI Approved :: MIT License
Classifier: Operating System :: POSIX :: Linux
Classifier: Programming Language :: Python :: 3
Classifier: Programming Language :: Python :: 3.6
Classifier: Topic :: Multimedia :: Sound/Audio
Classifier: Topic :: Multimedia :: Video
Classifier: Topic :: Utilities
